{
    "version": "12.0",
    "description": "Free and simple software for turning digital photos to the correct orientation.",
    "homepage": "https://annystudio.com/software/jpeglosslessrotator/",
    "url": "https://annystudio.com/jpegr_portable_64bit.zip",
    "hash": "d71133c5d933a027a2bbc1b97dd068c6f37b8d0c332c5e843597b03e19694690",
    "checkver": {
        "url": "https://annystudio.com/software/jpeglosslessrotator/",
        "re": "Download free JPEG Lossless Rotator ((\\d+\\.)+\\d+) portable.*"
    },
    "shortcuts": [
        [
            "jpegr.exe",
            "JPEG Lossless Rotator"
        ]
    ],
    "persist": "jpegr.ini",
    "extract_dir": "jpegr_portable_64bit",
    "autoupdate": {
        "url": "https://annystudio.com/jpegr_portable_64bit.zip"
    }
}
