{
    "homepage": "https://github.com/ggml-org/llama.cpp",
    "version": "b5006",
    "description": "Inference of Meta's LLaMA model (and others) in pure C/C++",
    "checkver": {
        "url": "https://github.com/ggml-org/llama.cpp/releases/latest",
        "re": "llama.cpp/releases/tag/(.*?)&.*?data-view-component=\"true\""
    },
    "url": "https://github.com/ggml-org/llama.cpp/releases/download/b5006/llama-b5006-bin-win-cuda-cu12.4-x64.zip",
    "hash": "9516668c1fbde2b8afc69b2c4aa0b97bf1c346afe6547fcee4580ccccacf1c8b",
    "autoupdate": {
        "url": "https://github.com/ggml-org/llama.cpp/releases/download/$version/llama-$version-bin-win-cuda-cu12.4-x64.zip"
    }
}
