{
    "homepage": "https://github.com/ggml-org/llama.cpp",
    "version": "b4977",
    "description": "Inference of Meta's LLaMA model (and others) in pure C/C++",
    "checkver": {
        "url": "https://github.com/ggml-org/llama.cpp/releases/latest",
        "re": "llama.cpp/releases/tag/(.*?)&.*?data-view-component=\"true\""
    },
    "url": "https://github.com/ggml-org/llama.cpp/releases/download/b4977/llama-b4977-bin-win-avx2-x64.zip",
    "hash": "b689d02edd5d33d4005f57c519982af03e3a54331effc55c0cb496ae17f1ad4f",
    "autoupdate": {
        "url": "https://github.com/ggml-org/llama.cpp/releases/download/$version/llama-$version-bin-win-avx2-x64.zip"
    }
}
