{
    "homepage": "https://github.com/ggml-org/llama.cpp",
    "version": "b4882",
    "description": "Inference of Meta's LLaMA model (and others) in pure C/C++",
    "checkver": {
        "url": "https://github.com/ggml-org/llama.cpp/releases/latest",
        "re": "llama.cpp/releases/tag/(.*?)&.*?data-view-component=\"true\""
    },
    "url": "https://github.com/ggml-org/llama.cpp/releases/download/b4882/llama-b4882-bin-win-cuda-cu12.4-x64.zip",
    "hash": "8fa6a2e527d5ff014b78f7958f7f2593d4b1130c64da38838f4b866becb2c4f6",
    "autoupdate": {
        "url": "https://github.com/ggml-org/llama.cpp/releases/download/$version/llama-$version-bin-win-cuda-cu12.4-x64.zip"
    }
}
