{
    "homepage": "https://github.com/ggml-org/llama.cpp",
    "version": "b4876",
    "description": "Inference of Meta's LLaMA model (and others) in pure C/C++",
    "checkver": {
        "url": "https://github.com/ggml-org/llama.cpp/releases/latest",
        "re": "llama.cpp/releases/tag/(.*?)&.*?data-view-component=\"true\""
    },
    "url": "https://github.com/ggml-org/llama.cpp/releases/download/b4876/llama-b4876-bin-win-cuda-cu12.4-x64.zip",
    "hash": "47dba99de71a2bcaf3b031411b2cb512ffd9a7cd903a33af7467d321eebbf577",
    "autoupdate": {
        "url": "https://github.com/ggml-org/llama.cpp/releases/download/$version/llama-$version-bin-win-cuda-cu12.4-x64.zip"
    }
}
