{
    "homepage": "https://github.com/ggml-org/llama.cpp",
    "version": "b4749",
    "description": "Inference of Meta's LLaMA model (and others) in pure C/C++",
    "checkver": {
        "url": "https://github.com/ggml-org/llama.cpp/releases/latest",
        "re": "llama.cpp/releases/tag/(.*?)&.*?data-view-component=\"true\""
    },
    "url": "https://github.com/ggml-org/llama.cpp/releases/download/b4749/llama-b4749-bin-win-avx2-x64.zip",
    "hash": "c19284d52144df00f733551f5b9e7ce0340e5fdc2cd96e1590ab4fc8319b5f66",
    "autoupdate": {
        "url": "https://github.com/ggml-org/llama.cpp/releases/download/$version/llama-$version-bin-win-avx2-x64.zip"
    }
}
