{
    "homepage": "https://github.com/ggml-org/llama.cpp",
    "version": "b4827",
    "description": "Inference of Meta's LLaMA model (and others) in pure C/C++",
    "checkver": {
        "url": "https://github.com/ggml-org/llama.cpp/releases/latest",
        "re": "llama.cpp/releases/tag/(.*?)&.*?data-view-component=\"true\""
    },
    "url": "https://github.com/ggml-org/llama.cpp/releases/download/b4827/llama-b4827-bin-win-cuda-cu12.4-x64.zip",
    "hash": "339c9c76cf94e4f23f18bdc12a00359dbd0ea64aa5cc89adfd8a2b3016c7adb9",
    "autoupdate": {
        "url": "https://github.com/ggml-org/llama.cpp/releases/download/$version/llama-$version-bin-win-cuda-cu12.4-x64.zip"
    }
}
