{
    "homepage": "https://github.com/ggml-org/llama.cpp",
    "version": "b4818",
    "description": "Inference of Meta's LLaMA model (and others) in pure C/C++",
    "checkver": {
        "url": "https://github.com/ggml-org/llama.cpp/releases/latest",
        "re": "llama.cpp/releases/tag/(.*?)&.*?data-view-component=\"true\""
    },
    "url": "https://github.com/ggml-org/llama.cpp/releases/download/b4818/llama-b4818-bin-win-cuda-cu12.4-x64.zip",
    "hash": "cdbd8dbf884261e3bc7de9217306d63d61467af6a7ffadefdb1a9d29c7fd67ec",
    "autoupdate": {
        "url": "https://github.com/ggml-org/llama.cpp/releases/download/$version/llama-$version-bin-win-cuda-cu12.4-x64.zip"
    }
}
