{
    "homepage": "https://github.com/ggml-org/llama.cpp",
    "version": "b4847",
    "description": "Inference of Meta's LLaMA model (and others) in pure C/C++",
    "checkver": {
        "url": "https://github.com/ggml-org/llama.cpp/releases/latest",
        "re": "llama.cpp/releases/tag/(.*?)&.*?data-view-component=\"true\""
    },
    "url": "https://github.com/ggml-org/llama.cpp/releases/download/b4847/llama-b4847-bin-win-avx2-x64.zip",
    "hash": "0d34d1a6e386da99af9d241a865d1930ff6d6083ba19b35757eb64200b1a6dd3",
    "autoupdate": {
        "url": "https://github.com/ggml-org/llama.cpp/releases/download/$version/llama-$version-bin-win-avx2-x64.zip"
    }
}
