{
    "homepage": "https://github.com/ggml-org/llama.cpp",
    "version": "b5204",
    "description": "Inference of Meta's LLaMA model (and others) in pure C/C++",
    "checkver": {
        "url": "https://github.com/ggml-org/llama.cpp/releases/latest",
        "re": "llama.cpp/releases/tag/(.*?)&.*?data-view-component=\"true\""
    },
    "url": "https://github.com/ggml-org/llama.cpp/releases/download/b5204/llama-b5204-bin-win-avx2-x64.zip",
    "hash": "d72a980b8cca272da7e7a7a60a5f96e8c7ae386a48f1408c2d6fa500c00c6601",
    "autoupdate": {
        "url": "https://github.com/ggml-org/llama.cpp/releases/download/$version/llama-$version-bin-win-avx2-x64.zip"
    }
}
