{
    "version": "2.53.5",
    "architecture": {
        "64bit": {
            "url": "https://github.com/bcpierce00/unison/releases/download/v2.53.5/unison-2.53.5-windows-x86_64.zip",
            "hash": "20ac71059a2497ce71b1ab5eb72ac0fb6910526d4c9885fe2aa85dec2edd0850"
        }
    },
    "description": "A file-synchronization tool.",
    "homepage": "https://www.cis.upenn.edu/~bcpierce/unison",
    "license": "GPL-3.0-only",
    "checkver": {
        "url": "https://github.com/bcpierce00/unison/releases/latest",
        "regex": ">v((\\d+\\.)+(\\d+))<\\/h1>",
        "reverse": true
    },
    "autoupdate": {
        "architecture": {
            "64bit": {
                "url": "https://github.com/bcpierce00/unison/releases/download/v$version/unison-$version-windows-x86_64.zip"
            }
        }
    }
}
