{
    "homepage": "https://github.com/errata-ai/vale",
    "version": "2.10.7",
    "description": "Vale is a command-line tool that brings code-like linting to prose.",
    "checkver": {
        "url": "https://github.com/errata-ai/vale/releases/latest",
        "re": "v([\\d.]+[\\d](-rc..)?)<"
    },
    "architecture": {
        "64bit": {
            "url": "https://github.com/errata-ai/vale/releases/download/v2.10.7/vale_2.10.7_Windows_64-bit.zip",
            "hash": "06820f2691fb35db0dcea33b8b355a614c5eadb6cc4fac1e6980714cf8341947"
        },
        "32bit": {
            "url": "https://github.com/errata-ai/vale/releases/download/v2.10.7/vale_2.10.7_Windows_64-bit.zip",
            "hash": "06820f2691fb35db0dcea33b8b355a614c5eadb6cc4fac1e6980714cf8341947"
        }
    },
    "autoupdate": {
        "url": "https://github.com/errata-ai/vale/releases/download/v$version/vale_$version_Windows_64-bit.zip"
    },
    "bin": "vale.exe"
}
